Metadata-Version: 2.1
Name: flaskvel
Version: 2.1
Summary: A small package for validating incoming HTTP requests
Home-page: https://github.com/bogdan9898/flaskvel
Author: Bogdan Istoc
Author-email: bogdan.istoc98@gmail.com
License: MIT
Download-URL: https://github.com/bogdan9898/flaskvel/archive/refs/tags/v2.1.tar.gz
Keywords: flask,http,validator,request validator,http validator
Platform: UNKNOWN
Classifier: Development Status :: 5 - Production/Stable
Classifier: Intended Audience :: Developers
Classifier: Topic :: Software Development :: Build Tools
Classifier: License :: OSI Approved :: MIT License
Classifier: Programming Language :: Python :: 3
Classifier: Programming Language :: Python :: 3.6
Classifier: Programming Language :: Python :: 3.7
Classifier: Programming Language :: Python :: 3.8
Requires-Python: >=3.6
License-File: LICENSE.txt
